mucstpy/MuCST.py
mucstpy/__init__.py
mucstpy/image_feature.py
mucstpy/loss.py
mucstpy/model.py
mucstpy/utils.py
mucstpy-1.0.7.dist-info/LICENSE
mucstpy-1.0.7.dist-info/METADATA
mucstpy-1.0.7.dist-info/WHEEL
mucstpy-1.0.7.dist-info/top_level.txt
mucstpy-1.0.7.dist-info/RECORD
