Metadata-Version: 2.1
Name: mucstpy
Version: 1.0.7
Summary: The initial package of MuCST
Author-email: Yu Wang <qq352542417@gmail.com>
Project-URL: Homepage, https://github.com/xkmaxidian/MuCST
Project-URL: Issues, https://github.com/xkmaxidian/MuCST/issues
Classifier: Programming Language :: Python :: 3
Classifier: License :: OSI Approved :: MIT License
Classifier: Operating System :: OS Independent
Requires-Python: >=3.8
License-File: LICENSE
Requires-Dist: scanpy >=1.9.3
Requires-Dist: numpy
Requires-Dist: pandas
Requires-Dist: anndata
Requires-Dist: matplotlib
Requires-Dist: scipy
Requires-Dist: scikit-learn
Requires-Dist: psutil
Requires-Dist: tqdm
Requires-Dist: leidenalg
Requires-Dist: torch >=2.0
Requires-Dist: torchvision
Requires-Dist: pathlib
Requires-Dist: POT
Requires-Dist: rpy2
